example/__init__.py
example/__main__.py
example/cloud/__init__.py
example/cloud/mqtt.py
example/models/__init__.py
example/models/system.py
example/models/telemetry.py
example/sensors/__init__.py
example/sensors/uart.py
myosin/__init__.py
myosin/__version__.py
myosin/exceptions/__init__.py
myosin/exceptions/cache.py
myosin/exceptions/state.py
myosin/models/__init__.py
myosin/models/state.py
myosin/state/__init__.py
myosin/state/ssm.py
myosin/state/state.py
myosin/typing/__init__.py
myosin/utils/__init__.py
myosin/utils/funcs.py
myosin/utils/metrics.py
tests/__init__.py
tests/test_ssm.py
tests/test_state.py
tests/test_state_model.py
tests/resources/__init__.py
tests/resources/errors.py
tests/resources/models.py
myosin-0.2.3.dist-info/LICENSE
myosin-0.2.3.dist-info/METADATA
myosin-0.2.3.dist-info/WHEEL
myosin-0.2.3.dist-info/top_level.txt
myosin-0.2.3.dist-info/RECORD
