Metadata-Version: 2.1
Name: myosin
Version: 0.2.3
Summary: Lightweight state management engine for embedded linux
Home-page: https://github.com/ztnel/myosin
Author: Christian Sargusingh
Author-email: christian@leapsystems.online
License: UNKNOWN
Project-URL: Documentation, https://myosin.readthedocs.io
Project-URL: Github, https://github.com/ztnel/myosin
Platform: UNKNOWN
Classifier: Operating System :: Unix
Classifier: Development Status :: 4 - Beta
Classifier: Programming Language :: Python :: 3.8
Classifier: Programming Language :: Python :: 3.9
Classifier: Programming Language :: Python :: 3.10
Classifier: License :: OSI Approved :: MIT License
Classifier: Topic :: Software Development :: Object Brokering
Classifier: Topic :: Software Development :: Embedded Systems
Requires-Python: >=3.8.0
License-File: LICENSE
Requires-Dist: prometheus-client (==0.16.0)
